Metadata-Version: 2.1
Name: naruno-scan
Version: 0.1.1
Summary: Scan website for Naruno
Home-page: https://github.com/Naruno/scan
Author: Onur Atakan ULUSOY
Author-email: onur.atakan.ulusoy@naruno.org
License: MPL-2.0
Platform: UNKNOWN
Requires-Python: >= 3
